MANIFEST.in
README.rst
setup.cfg
setup.py
bin/rpn
rpn/__init__.py
rpn/rpn.py
rpn.egg-info/PKG-INFO
rpn.egg-info/SOURCES.txt
rpn.egg-info/dependency_links.txt
rpn.egg-info/top_level.txt