Metadata-Version: 1.0
Name: rpn
Version: 1.0
Summary: Reverse Polish Notation calculator.
Home-page: https://github.com/dustinrohde/python-rpn
Author: Dustin Rohde
Author-email: xdrohdex@gmail.com
License: MIT
Keywords: math calculator rpn arithmetic
Platform: UNKNOWN
